libname/101917205.py
libname/__init__.py
Topsis_Ketan_101917205-1.0.0.dist-info/METADATA
Topsis_Ketan_101917205-1.0.0.dist-info/WHEEL
Topsis_Ketan_101917205-1.0.0.dist-info/top_level.txt
Topsis_Ketan_101917205-1.0.0.dist-info/RECORD
