Metadata-Version: 2.1
Name: Topsis-Ketan-101917205
Version: 1.0.0
Summary: Topsis Code
Home-page: UNKNOWN
Author: Ketan
Author-email: <sabharwalketan05@gmail.com>
License: UNKNOWN
Keywords: python
Platform: UNKNOWN
Classifier: Development Status :: 1 - Planning
Classifier: Intended Audience :: Developers
Classifier: Programming Language :: Python :: 3
Classifier: Operating System :: Unix
Classifier: Operating System :: MacOS :: MacOS X
Classifier: Operating System :: Microsoft :: Windows
